{
    "name": "Universe One",
    "stars": [
        {
            "id": "0",
            "name": "EA-470",
            "type": "system",
            "coordinates": {
                "x": 11.13,
                "y": -95.94,
                "z": 24.29
            },
            "children": [
                {
                    "id": "0-0",
                    "name": "EA-470 Star",
                    "type": "star",
                    "size": 1.97,
                    "info": "!createInfo",
                    "children": []
                }
            ]
        },
        {
            "id": "1",
            "name": "E-3",
            "type": "system",
            "coordinates": {
                "x": -66.78,
                "y": 7.94,
                "z": -56.93
            },
            "children": [
                {
                    "id": "1-0",
                    "name": "E-3 Star",
                    "type": "star",
                    "size": 2.34,
                    "info": "!createInfo",
                    "children": [
                        {
                            "id": "1-0-0",
                            "name": "Teszt star",
                            "type": "star",
                            "size": 2.62,
                            "distance": 0.87,
                            "info": "!createInfo",
                            "children": []
                        },
                        {
                            "id": "1-0-1",
                            "name": "Teszt planet",
                            "type": "planet",
                            "size": 0.45,
                            "distance": 6.29,
                            "info": "!createInfo",
                            "children": []
                        },
                        {
                            "id": "1-0-2",
                            "name": "Teszt planet",
                            "type": "planet",
                            "size": 0.09,
                            "distance": 2.42,
                            "info": "!createInfo",
                            "children": [
                                {
                                    "id": "1-0-2-0",
                                    "name": "Teszt planet",
                                    "type": "planet",
                                    "size": 0.64,
                                    "distance": 0.3,
                                    "info": "!createInfo",
                                    "children": []
                                }
                            ]
                        }
                    ]
                }
            ]
        },
        {
            "id": "2",
            "name": "AAB-458",
            "type": "system",
            "coordinates": {
                "x": 24.59,
                "y": 44.52,
                "z": 82.48
            },
            "children": [
                {
                    "id": "2-0",
                    "name": "AAB-458 Star",
                    "type": "star",
                    "size": 0.05,
                    "info": "!createInfo",
                    "children": [
                        {
                            "id": "2-0-0",
                            "name": "Teszt planet",
                            "type": "planet",
                            "size": 0.56,
                            "distance": 9.97,
                            "info": "!createInfo",
                            "children": [
                                {
                                    "id": "2-0-0-0",
                                    "name": "Teszt planet",
                                    "type": "planet",
                                    "size": 0.48,
                                    "distance": 6.69,
                                    "info": "!createInfo",
                                    "children": [
                                        {
                                            "id": "2-0-0-0-0",
                                            "name": "Teszt planet",
                                            "type": "planet",
                                            "size": 0.06,
                                            "distance": 0.98,
                                            "info": "!createInfo",
                                            "children": []
                                        }
                                    ]
                                }
                            ]
                        },
                        {
                            "id": "2-0-1",
                            "name": "Teszt station",
                            "type": "station",
                            "distance": 5.17,
                            "info": "!createInfo",
                            "services": "!createServices"
                        },
                        {
                            "id": "2-0-2",
                            "name": "Teszt planet",
                            "type": "planet",
                            "size": 1,
                            "distance": 3.93,
                            "info": "!createInfo",
                            "children": []
                        }
                    ]
                }
            ]
        },
        {
            "id": "3",
            "name": "EBBF-552",
            "type": "system",
            "coordinates": {
                "x": -75.11,
                "y": 19.65,
                "z": 60.18
            },
            "children": [
                {
                    "id": "3-0",
                    "name": "EBBF-552 Star",
                    "type": "star",
                    "size": 1.45,
                    "info": "!createInfo",
                    "children": [
                        {
                            "id": "3-0-0",
                            "name": "Teszt station",
                            "type": "station",
                            "distance": 2.58,
                            "info": "!createInfo",
                            "services": "!createServices"
                        },
                        {
                            "id": "3-0-1",
                            "name": "Teszt station",
                            "type": "station",
                            "distance": 1.79,
                            "info": "!createInfo",
                            "services": "!createServices"
                        }
                    ]
                }
            ]
        },
        {
            "id": "4",
            "name": "FDCB-67",
            "type": "system",
            "coordinates": {
                "x": -70.03,
                "y": 33.72,
                "z": -74.14
            },
            "children": [
                {
                    "id": "4-0",
                    "name": "FDCB-67 Star",
                    "type": "star",
                    "size": 1.68,
                    "info": "!createInfo",
                    "children": [
                        {
                            "id": "4-0-0",
                            "name": "Teszt planet",
                            "type": "planet",
                            "size": 0.52,
                            "distance": 8.3,
                            "info": "!createInfo",
                            "children": []
                        },
                        {
                            "id": "4-0-1",
                            "name": "Teszt planet",
                            "type": "planet",
                            "size": 0.66,
                            "distance": 1.17,
                            "info": "!createInfo",
                            "children": []
                        },
                        {
                            "id": "4-0-2",
                            "name": "Teszt planet",
                            "type": "planet",
                            "size": 0.77,
                            "distance": 1.13,
                            "info": "!createInfo",
                            "children": []
                        }
                    ]
                }
            ]
        },
        {
            "id": "5",
            "name": "DEE-8",
            "type": "system",
            "coordinates": {
                "x": -46.78,
                "y": 29.83,
                "z": 86.66
            },
            "children": [
                {
                    "id": "5-0",
                    "name": "DEE-8 Star",
                    "type": "star",
                    "size": 4.58,
                    "info": "!createInfo",
                    "children": []
                }
            ]
        },
        {
            "id": "6",
            "name": "CAE-64",
            "type": "system",
            "coordinates": {
                "x": 77.7,
                "y": 42.94,
                "z": -59.64
            },
            "children": [
                {
                    "id": "6-0",
                    "name": "CAE-64 Star",
                    "type": "star",
                    "size": 1.68,
                    "info": "!createInfo",
                    "children": [
                        {
                            "id": "6-0-0",
                            "name": "Teszt station",
                            "type": "station",
                            "distance": 5.84,
                            "info": "!createInfo",
                            "services": "!createServices"
                        },
                        {
                            "id": "6-0-1",
                            "name": "Teszt station",
                            "type": "station",
                            "distance": 5.56,
                            "info": "!createInfo",
                            "services": "!createServices"
                        }
                    ]
                }
            ]
        },
        {
            "id": "7",
            "name": "E-22",
            "type": "system",
            "coordinates": {
                "x": 79.61,
                "y": -22.58,
                "z": 85.85
            },
            "children": [
                {
                    "id": "7-0",
                    "name": "E-22 Star",
                    "type": "star",
                    "size": 3.72,
                    "info": "!createInfo",
                    "children": []
                }
            ]
        },
        {
            "id": "8",
            "name": "DECB-89",
            "type": "system",
            "coordinates": {
                "x": 83.5,
                "y": -65.56,
                "z": -46.15
            },
            "children": [
                {
                    "id": "8-0",
                    "name": "DECB-89 Star",
                    "type": "star",
                    "size": 3.35,
                    "info": "!createInfo",
                    "children": [
                        {
                            "id": "8-0-0",
                            "name": "Teszt planet",
                            "type": "planet",
                            "size": 0.22,
                            "distance": 8.99,
                            "info": "!createInfo",
                            "children": []
                        },
                        {
                            "id": "8-0-1",
                            "name": "Teszt planet",
                            "type": "planet",
                            "size": 0.99,
                            "distance": 2.56,
                            "info": "!createInfo",
                            "children": [
                                {
                                    "id": "8-0-1-0",
                                    "name": "Teszt planet",
                                    "type": "planet",
                                    "size": 0.25,
                                    "distance": 5.93,
                                    "info": "!createInfo",
                                    "children": []
                                }
                            ]
                        },
                        {
                            "id": "8-0-2",
                            "name": "Teszt planet",
                            "type": "planet",
                            "size": 0.8,
                            "distance": 4.16,
                            "info": "!createInfo",
                            "children": []
                        }
                    ]
                }
            ]
        },
        {
            "id": "9",
            "name": "DBB-43",
            "type": "system",
            "coordinates": {
                "x": -4.07,
                "y": 57.85,
                "z": -21.37
            },
            "children": [
                {
                    "id": "9-0",
                    "name": "DBB-43 Star",
                    "type": "star",
                    "size": 0.55,
                    "info": "!createInfo",
                    "children": [
                        {
                            "id": "9-0-0",
                            "name": "Teszt planet",
                            "type": "planet",
                            "size": 0.4,
                            "distance": 2.15,
                            "info": "!createInfo",
                            "children": [
                                {
                                    "id": "9-0-0-0",
                                    "name": "Teszt planet",
                                    "type": "planet",
                                    "size": 0.64,
                                    "distance": 2.74,
                                    "info": "!createInfo",
                                    "children": []
                                }
                            ]
                        },
                        {
                            "id": "9-0-1",
                            "name": "Teszt planet",
                            "type": "planet",
                            "size": 0.15,
                            "distance": 5.86,
                            "info": "!createInfo",
                            "children": []
                        }
                    ]
                }
            ]
        },
        {
            "id": "10",
            "name": "ECC-24",
            "type": "system",
            "coordinates": {
                "x": -81.48,
                "y": -71.3,
                "z": -33.41
            },
            "children": [
                {
                    "id": "10-0",
                    "name": "ECC-24 Star",
                    "type": "star",
                    "size": 3.65,
                    "info": "!createInfo",
                    "children": [
                        {
                            "id": "10-0-0",
                            "name": "Teszt planet",
                            "type": "planet",
                            "size": 0.38,
                            "distance": 0.35,
                            "info": "!createInfo",
                            "children": []
                        },
                        {
                            "id": "10-0-1",
                            "name": "Teszt star",
                            "type": "star",
                            "size": 2.8,
                            "distance": 3.07,
                            "info": "!createInfo",
                            "children": []
                        },
                        {
                            "id": "10-0-2",
                            "name": "Teszt planet",
                            "type": "planet",
                            "size": 0.35,
                            "distance": 2.59,
                            "info": "!createInfo",
                            "children": [
                                {
                                    "id": "10-0-2-0",
                                    "name": "Teszt planet",
                                    "type": "planet",
                                    "size": 0.51,
                                    "distance": 1.2,
                                    "info": "!createInfo",
                                    "children": []
                                }
                            ]
                        }
                    ]
                }
            ]
        },
        {
            "id": "11",
            "name": "EEE-786",
            "type": "system",
            "coordinates": {
                "x": -12.82,
                "y": 57.66,
                "z": -17.11
            },
            "children": [
                {
                    "id": "11-0",
                    "name": "EEE-786 Star",
                    "type": "star",
                    "size": 3.44,
                    "info": "!createInfo",
                    "children": [
                        {
                            "id": "11-0-0",
                            "name": "Teszt planet",
                            "type": "planet",
                            "size": 0.24,
                            "distance": 2.43,
                            "info": "!createInfo",
                            "children": [
                                {
                                    "id": "11-0-0-0",
                                    "name": "Teszt planet",
                                    "type": "planet",
                                    "size": 0.33,
                                    "distance": 1.02,
                                    "info": "!createInfo",
                                    "children": []
                                }
                            ]
                        }
                    ]
                }
            ]
        },
        {
            "id": "12",
            "name": "EC-184",
            "type": "system",
            "coordinates": {
                "x": -21.34,
                "y": 10.82,
                "z": -69.56
            },
            "children": [
                {
                    "id": "12-0",
                    "name": "EC-184 Star",
                    "type": "star",
                    "size": 4.71,
                    "info": "!createInfo",
                    "children": []
                }
            ]
        },
        {
            "id": "13",
            "name": "BFB-38",
            "type": "system",
            "coordinates": {
                "x": -84.75,
                "y": 86.28,
                "z": 61.88
            },
            "children": [
                {
                    "id": "13-0",
                    "name": "BFB-38 Star",
                    "type": "star",
                    "size": 3.2,
                    "info": "!createInfo",
                    "children": [
                        {
                            "id": "13-0-0",
                            "name": "Teszt planet",
                            "type": "planet",
                            "size": 0.78,
                            "distance": 8.31,
                            "info": "!createInfo",
                            "children": [
                                {
                                    "id": "13-0-0-0",
                                    "name": "Teszt planet",
                                    "type": "planet",
                                    "size": 0.12,
                                    "distance": 8.12,
                                    "info": "!createInfo",
                                    "children": []
                                }
                            ]
                        },
                        {
                            "id": "13-0-1",
                            "name": "Teszt planet",
                            "type": "planet",
                            "size": 0.2,
                            "distance": 7.11,
                            "info": "!createInfo",
                            "children": [
                                null
                            ]
                        },
                        {
                            "id": "13-0-2",
                            "name": "Teszt planet",
                            "type": "planet",
                            "size": 0.88,
                            "distance": 8.52,
                            "info": "!createInfo",
                            "children": [
                                {
                                    "id": "13-0-2-0",
                                    "name": "Teszt planet",
                                    "type": "planet",
                                    "size": 0.71,
                                    "distance": 6.52,
                                    "info": "!createInfo",
                                    "children": []
                                }
                            ]
                        }
                    ]
                }
            ]
        },
        {
            "id": "14",
            "name": "BED-77",
            "type": "system",
            "coordinates": {
                "x": -32.81,
                "y": -69.48,
                "z": 49.53
            },
            "children": [
                {
                    "id": "14-0",
                    "name": "BED-77 Star",
                    "type": "star",
                    "size": 0.55,
                    "info": "!createInfo",
                    "children": []
                }
            ]
        },
        {
            "id": "15",
            "name": "CD-34",
            "type": "system",
            "coordinates": {
                "x": 50.15,
                "y": -0.74,
                "z": -2.18
            },
            "children": [
                {
                    "id": "15-0",
                    "name": "CD-34 Star",
                    "type": "star",
                    "size": 0.91,
                    "info": "!createInfo",
                    "children": [
                        {
                            "id": "15-0-0",
                            "name": "Teszt planet",
                            "type": "planet",
                            "size": 0.51,
                            "distance": 2.36,
                            "info": "!createInfo",
                            "children": [
                                {
                                    "id": "15-0-0-0",
                                    "name": "Teszt station",
                                    "type": "station",
                                    "distance": 4.85,
                                    "info": "!createInfo",
                                    "services": "!createServices"
                                }
                            ]
                        },
                        {
                            "id": "15-0-1",
                            "name": "Teszt planet",
                            "type": "planet",
                            "size": 0.11,
                            "distance": 7.61,
                            "info": "!createInfo",
                            "children": [
                                {
                                    "id": "15-0-1-0",
                                    "name": "Teszt planet",
                                    "type": "planet",
                                    "size": 0.39,
                                    "distance": 5.81,
                                    "info": "!createInfo",
                                    "children": [
                                        {
                                            "id": "15-0-1-0-0",
                                            "name": "Teszt planet",
                                            "type": "planet",
                                            "size": 0.37,
                                            "distance": 1.61,
                                            "info": "!createInfo",
                                            "children": []
                                        }
                                    ]
                                }
                            ]
                        },
                        {
                            "id": "15-0-2",
                            "name": "Teszt planet",
                            "type": "planet",
                            "size": 0.17,
                            "distance": 3.42,
                            "info": "!createInfo",
                            "children": []
                        }
                    ]
                }
            ]
        },
        {
            "id": "16",
            "name": "BB-25",
            "type": "system",
            "coordinates": {
                "x": 23.02,
                "y": 18.81,
                "z": 7.75
            },
            "children": [
                {
                    "id": "16-0",
                    "name": "BB-25 Star",
                    "type": "star",
                    "size": 0.79,
                    "info": "!createInfo",
                    "children": []
                }
            ]
        },
        {
            "id": "17",
            "name": "D-7",
            "type": "system",
            "coordinates": {
                "x": 79.38,
                "y": -80.28,
                "z": -8.86
            },
            "children": [
                {
                    "id": "17-0",
                    "name": "D-7 Star",
                    "type": "star",
                    "size": 0.07,
                    "info": "!createInfo",
                    "children": [
                        {
                            "id": "17-0-0",
                            "name": "Teszt planet",
                            "type": "planet",
                            "size": 0.99,
                            "distance": 2.1,
                            "info": "!createInfo",
                            "children": []
                        }
                    ]
                }
            ]
        },
        {
            "id": "18",
            "name": "C-12",
            "type": "system",
            "coordinates": {
                "x": -62.46,
                "y": -58.63,
                "z": 67.33
            },
            "children": [
                {
                    "id": "18-0",
                    "name": "C-12 Star",
                    "type": "star",
                    "size": 1.55,
                    "info": "!createInfo",
                    "children": []
                }
            ]
        },
        {
            "id": "19",
            "name": "C-74",
            "type": "system",
            "coordinates": {
                "x": -60.92,
                "y": 60.04,
                "z": -30.78
            },
            "children": [
                {
                    "id": "19-0",
                    "name": "C-74 Star",
                    "type": "star",
                    "size": 3.77,
                    "info": "!createInfo",
                    "children": [
                        {
                            "id": "19-0-0",
                            "name": "Teszt planet",
                            "type": "planet",
                            "size": 0.16,
                            "distance": 5.05,
                            "info": "!createInfo",
                            "children": []
                        },
                        {
                            "id": "19-0-1",
                            "name": "Teszt planet",
                            "type": "planet",
                            "size": 0.85,
                            "distance": 5.38,
                            "info": "!createInfo",
                            "children": [
                                {
                                    "id": "19-0-1-0",
                                    "name": "Teszt planet",
                                    "type": "planet",
                                    "size": 0.71,
                                    "distance": 4.59,
                                    "info": "!createInfo",
                                    "children": []
                                }
                            ]
                        }
                    ]
                }
            ]
        }
    ]
}